yoli/__init__.py
yoli/main.py
yoli/weights/yolov10n.pt
yoli-0.0.0.dist-info/METADATA
yoli-0.0.0.dist-info/WHEEL
yoli-0.0.0.dist-info/entry_points.txt
yoli-0.0.0.dist-info/RECORD
