Metadata-Version: 2.1
Name: yoli
Version: 0.0.0
Summary: A simply cli app that indexes videos using YOLOv10
Author: drbh
Author-email: david.richard.holtz@gmail.com
Requires-Python: >=3.11,<4.0
Classifier: Programming Language :: Python :: 3
Classifier: Programming Language :: Python :: 3.11
Classifier: Programming Language :: Python :: 3.12
